<?xml version="1.0" encoding="UTF-8" standalone="yes"?>
<releve RIB="011112222333344445555666">
    <dateReleve>2021-11-10+01:00</dateReleve>
    <solde>14500</solde>
    <operations dateDebut="2021-01-01+01:00" dateFin="2021-01-30+01:00">
        <operationList type="CREDIT" date="2021-01-01+01:00" montant="9000.0" description="Vers Espèce"/>
        <operationList type="DEBIT" date="2021-01-11+01:00" montant="3400.0" description="Chèque Guichet"/>
        <operationList type="DEBIT" date="2021-01-15+01:00" montant="120.0" description="Prélèvement Assurence"/>
        <operationList type="CREDIT" date="2021-01-25+01:00" montant="70000.0" description="Virement .."/>
    </operations>
</releve>
